boosty_api/__init__.py
boosty_api/boosty_api.py
boosty_api/enums.py
boosty_api/exceptions.py
boosty_api/models.py
boosty_api/utils.py
boosty_api-1.0.0.dist-info/licenses/LICENSE
examples/current-user.py
boosty_api-1.0.0.dist-info/METADATA
boosty_api-1.0.0.dist-info/WHEEL
boosty_api-1.0.0.dist-info/top_level.txt
boosty_api-1.0.0.dist-info/RECORD
