Metadata-Version: 2.4
Name: boosty-api
Version: 1.0.0
Summary: Boosty.to unofficial API client for authentication and user operations
Author-email: Kirill Vercetti <office@kyzima-spb.com>
License-Expression: MIT
Project-URL: Homepage, https://github.com/kyzima-spb/boosty-api
Project-URL: Repository, https://github.com/kyzima-spb/boosty-api
Project-URL: Issues, https://github.com/kyzima-spb/boosty-api/issues
Project-URL: Funding, https://mosg.info/donate
Keywords: boosty,boosty client,boosty api
Requires-Python: >=3.9
License-File: LICENSE
Requires-Dist: requests>=2.25
Provides-Extra: dev
Requires-Dist: mypy; extra == "dev"
Requires-Dist: setuptools-scm; extra == "dev"
Requires-Dist: types-requests; extra == "dev"
Dynamic: license-file
